qtexture/__init__.py
qtexture/monotones.py
qtexture/optimize.py
qtexture/prog_qaoa.py
qtexture/states.py
qtexture/utils.py
qtexture/kernels/_kernels.cpython-313-darwin.so
qtexture/kernels/bindings.cpp
qtexture/kernels/cpu_kernels.cpp
qtexture/kernels/kernels.metallib
qtexture/kernels/metal_kernels.mm
qtexture/validation/ising_model.py
qtexture-0.1.2.dist-info/METADATA
qtexture-0.1.2.dist-info/WHEEL
qtexture-0.1.2.dist-info/top_level.txt
qtexture-0.1.2.dist-info/RECORD
