Metadata-Version: 2.4
Name: qtexture
Version: 0.1.2
Summary: A library for calculating quantum state texture monotones.
Author-email: Cormac Kinsella <cormac.c.00@gmail.com>
Classifier: Programming Language :: Python :: 3
Classifier: License :: OSI Approved :: MIT License
Classifier: Operating System :: OS Independent
Classifier: Intended Audience :: Science/Research
Classifier: Topic :: Scientific/Engineering :: Physics
Requires-Python: >=3.8
Requires-Dist: numpy>=1.21
Requires-Dist: scipy>=1.8
Provides-Extra: qiskit
Requires-Dist: qiskit>=1.0; extra == "qiskit"
Provides-Extra: qutip
Requires-Dist: qutip>=4.7; extra == "qutip"
Provides-Extra: dev
Requires-Dist: matplotlib; extra == "dev"
Requires-Dist: qiskit; extra == "dev"
Requires-Dist: qutip; extra == "dev"
